aminofixasync/__init__.py
aminofixasync/acm.py
aminofixasync/client.py
aminofixasync/socket.py
aminofixasync/socket_old.py
aminofixasync/sub_client.py
aminofixasync/lib/__init__.py
aminofixasync/lib/util/__init__.py
aminofixasync/lib/util/device.py
aminofixasync/lib/util/exceptions.py
aminofixasync/lib/util/headers.py
aminofixasync/lib/util/helpers.py
aminofixasync/lib/util/objects.py
amino.fix_async-2.0.1.dist-info/LICENSE
amino.fix_async-2.0.1.dist-info/METADATA
amino.fix_async-2.0.1.dist-info/WHEEL
amino.fix_async-2.0.1.dist-info/top_level.txt
amino.fix_async-2.0.1.dist-info/RECORD
