Metadata-Version: 2.1
Name: amino.fix-async
Version: 2.0.1
Summary: Amino 2.0.3 fix lib. Discord - https://discord.gg/Bf3dpBRJHj
Home-page: https://github.com/Minori100/Amino.fix
Author: Minori
Author-email: 
License: MIT
Keywords: aminoapps,amino.fix-async,amino,amino-bot,narvii,api,python,python3,python3.x,minori
Platform: UNKNOWN
Requires-Python: >=3.6
Requires-Dist: aiohttp
Requires-Dist: requests
Requires-Dist: asyncio
Requires-Dist: typing
Requires-Dist: websocket-client (==0.57.0)
Requires-Dist: setuptools
Requires-Dist: json-minify
Requires-Dist: six
